abdel_langchain-0.1.2.dist-info/METADATA
abdel_langchain-0.1.2.dist-info/WHEEL
abdel_langchain-0.1.2.dist-info/entry_points.txt
abdel_langchain-0.1.2.dist-info/licenses/LICENSE
abdel_langchain/__init__.py
abdel_langchain-0.1.2.dist-info/RECORD
