Metadata-Version: 2.1
Name: abdel_langchain
Version: 0.1.2
Summary: A New Perspective on LangChain Design
Author-Email: Abdelrahman Abounida <abdelrahmanaboneda@gmail.com>
License: MIT
Requires-Python: >=3.11
Requires-Dist: httpx>=0.28.1
